MANIFEST.in
README.md
setup.cfg
setup.py
image2ipfs/__init__.py
image2ipfs/defaults.py
image2ipfs/git-revision
image2ipfs/main.py
image2ipfs.egg-info/PKG-INFO
image2ipfs.egg-info/SOURCES.txt
image2ipfs.egg-info/dependency_links.txt
image2ipfs.egg-info/entry_points.txt
image2ipfs.egg-info/not-zip-safe
image2ipfs.egg-info/requires.txt
image2ipfs.egg-info/top_level.txt