Metadata-Version: 1.0
Name: image2ipfs
Version: 0.0.7
Summary: Publish your docker image archives to IPFS
Home-page: https://github.com/jvassev/image2ipfs
Author: Julian Vassev
Author-email: jvassev@gmail.com
License: ASL 2
Platform: UNKNOWN
